tethys_apps/__init__.py
tethys_apps/admin.py
tethys_apps/app_installation.py
tethys_apps/apps.py
tethys_apps/context_processors.py
tethys_apps/decorators.py
tethys_apps/exceptions.py
tethys_apps/harvester.py
tethys_apps/models.py
tethys_apps/static_finders.py
tethys_apps/template_loaders.py
tethys_apps/terminal_colors.py
tethys_apps/urls.py
tethys_apps/utilities.py
tethys_apps/views.py
tethys_apps/base/__init__.py
tethys_apps/base/app_base.py
tethys_apps/base/bokeh_handler.py
tethys_apps/base/component_base.py
tethys_apps/base/controller.py
tethys_apps/base/function_extractor.py
tethys_apps/base/handoff.py
tethys_apps/base/mixins.py
tethys_apps/base/page_handler.py
tethys_apps/base/paths.py
tethys_apps/base/permissions.py
tethys_apps/base/url_map.py
tethys_apps/base/workspace.py
tethys_apps/base/testing/__init__.py
tethys_apps/base/testing/environment.py
tethys_apps/base/testing/testing.py
tethys_apps/management/__init__.py
tethys_apps/management/commands/__init__.py
tethys_apps/management/commands/collectworkspaces.py
tethys_apps/management/commands/pre_collectstatic.py
tethys_apps/management/commands/syncstores.py
tethys_apps/management/commands/tethys_app_uninstall.py
tethys_apps/migrations/0001_initial_41.py
tethys_apps/migrations/0002_auto_20230407_2337.py
tethys_apps/migrations/0003_proxyapp_display_external.py
tethys_apps/migrations/0004_rename_display_external_proxyapp_display_external_icon.py
tethys_apps/migrations/0005_customsettingbase_include_in_api.py
tethys_apps/migrations/0006_auto_20240401_2032.py
tethys_apps/migrations/0007_tethysapp_back_url.py
tethys_apps/migrations/__init__.py
tethys_apps/static/tethys_apps/css/app_base.min.css
tethys_apps/static/tethys_apps/css/app_content_only.css
tethys_apps/static/tethys_apps/css/feedback.css
tethys_apps/static/tethys_apps/css/loader.css
tethys_apps/static/tethys_apps/images/default_app_icon.gif
tethys_apps/static/tethys_apps/js/app_base.js
tethys_apps/static/tethys_apps/js/app_library.js
tethys_platform-4.4.2.dist-info/licenses/LICENSE
tethys_platform-4.4.2.dist-info/METADATA
tethys_platform-4.4.2.dist-info/WHEEL
tethys_platform-4.4.2.dist-info/entry_points.txt
tethys_platform-4.4.2.dist-info/top_level.txt
tethys_platform-4.4.2.dist-info/RECORD
