Metadata-Version: 2.4
Name: tethys-platform
Version: 4.4.2
Summary: Primary Tethys Platform Django Site Project
Author-email: Nathan Swain <nswain@aquaveo.com>, Scott Christensen <ScottyChristensen@gmail.com>
Project-URL: homepage, http://tethysplatform.org/
Project-URL: documentation, http://docs.tethysplatform.org/en/stable/
Project-URL: repository, https://github.com/tethysplatform/tethys
Keywords: web app,scientific,geospatial
Classifier: Environment :: Web Environment
Classifier: Framework :: Django
Classifier: Intended Audience :: Developers
Classifier: Operating System :: OS Independent
Classifier: Programming Language :: Python
Classifier: Programming Language :: Python :: 3
Classifier: Programming Language :: Python :: 3.10
Classifier: Topic :: Internet :: WWW/HTTP
Classifier: Topic :: Internet :: WWW/HTTP :: Dynamic Content
Requires-Python: >=3.10
License-File: LICENSE
Requires-Dist: pyopenssl
Requires-Dist: django<6,>=4.2
Requires-Dist: tornado<7,>=6.5
Requires-Dist: channels
Requires-Dist: daphne
Requires-Dist: requests<3,>=2.32.4
Requires-Dist: bcrypt
Requires-Dist: cryptography<45,>=44.0.1
Requires-Dist: pyyaml
Requires-Dist: jinja2
Requires-Dist: django-bootstrap5
Requires-Dist: django-model-utils
Requires-Dist: django-guardian
Requires-Dist: djangorestframework_simplejwt
Provides-Extra: test
Requires-Dist: pytest; extra == "test"
Requires-Dist: pytest-django; extra == "test"
Requires-Dist: pytest-cov; extra == "test"
Requires-Dist: requests_mock; extra == "test"
Provides-Extra: lint
Requires-Dist: flake8; extra == "lint"
Requires-Dist: black; extra == "lint"
Dynamic: license-file
